b3cdi/__init__.py
b3cdi/b3cdi.py
b3cdi/database.py
b3cdi/files_utils.py
b3cdi/scrapper.py
b3_cdi_curve-1.2.0.dist-info/LICENSE.txt
b3_cdi_curve-1.2.0.dist-info/METADATA
b3_cdi_curve-1.2.0.dist-info/WHEEL
b3_cdi_curve-1.2.0.dist-info/top_level.txt
b3_cdi_curve-1.2.0.dist-info/RECORD
