Metadata-Version: 2.1
Name: b3-cdi-curve
Version: 1.2.0
Summary: Create a local DB with the term structure of the Brazilian CDI curve (data from B3).
Home-page: https://github.com/fluxonaut/b3_cdi_curve
Author: Fluxonaut
Author-email: contact@fluxonaut.com
License: MIT
Platform: UNKNOWN
Classifier: License :: OSI Approved :: MIT License
Classifier: Programming Language :: Python :: 3.7
Requires-Dist: beautifulsoup4 (>=4.9.3)
Requires-Dist: numpy (>=1.19.2)
Requires-Dist: pandas (>=1.1.3)
Requires-Dist: pylint (>=2.6.0)
Requires-Dist: requests (>=2.24.0)
Requires-Dist: html5lib (>=1.1)
Requires-Dist: scipy (>=1.5.3)
Requires-Dist: rich (>=9.2.0)
